django_woah/__init__.py
django_woah/asgi.py
django_woah/authorization/__init__.py
django_woah/authorization/conditions.py
django_woah/authorization/context.py
django_woah/authorization/enum.py
django_woah/authorization/indirect_perms.py
django_woah/authorization/knowledge_base.py
django_woah/authorization/scheme.py
django_woah/authorization/solver.py
django_woah/drf/__init__.py
django_woah/drf/fields.py
django_woah/drf/permission.py
django_woah/drf/views.py
django_woah/migrations/0001_initial.py
django_woah/migrations/__init__.py
django_woah/models.py
django_woah/settings.py
django_woah/tests/__init__.py
django_woah/tests/test_utils.py
django_woah/urls.py
django_woah/utils/__init__.py
django_woah/utils/logic.py
django_woah/utils/models.py
django_woah/utils/q.py
django_woah/wsgi.py
django_woah-0.4.1.dist-info/LICENSE
django_woah-0.4.1.dist-info/METADATA
django_woah-0.4.1.dist-info/NOTICE
django_woah-0.4.1.dist-info/WHEEL
django_woah-0.4.1.dist-info/RECORD
