Metadata-Version: 2.3
Name: django-woah
Version: 0.4.1
Summary: A package intended to aid developers in implementing authorization for Django apps.
License: Apache-2.0
Keywords: django-woah,django,woah,authorization,permission,role,organization,team,drf,rest-framework
Author: Bogdan Petrea
Author-email: bogdan@presslabs.com
Maintainer: Bogdan Petrea
Maintainer-email: bogdan@presslabs.com
Requires-Python: >=3.11,<4.0
Classifier: License :: OSI Approved :: Apache Software License
Classifier: Programming Language :: Python :: 3
Classifier: Programming Language :: Python :: 3.11
Classifier: Programming Language :: Python :: 3.12
Classifier: Programming Language :: Python :: 3.13
Requires-Dist: django (>=4.2.10,<5.0.0)
Requires-Dist: uuid6 (>=2024.1.12,<2025.0.0)
Project-URL: Homepage, https://github.com/presslabs/django-woah/
Project-URL: Repository, https://github.com/presslabs/django-woah/
